[
  {
    "code": "417840",
    "content": "분기보고서를 통해 26년1분기 실적 발표. 연결기준 매출액 176.92억원(전년동기대비 +66.65%), 영업이익 40.72억원(전년동기대비 +147.39%), 순이익 46.05 억원(전년동기대비 +199.51%)"
  },
  {
    "code": "032800",
    "content": "전일 장 마감 후 운영자금 확보 목적으로 (주)엑스 대상 3,270,111주(49.99억원) 규모 제3자배정 유상증자 결정(발행가:1,529원, 상장예정:2026-06-11) 공시"
  },
  {
    "code": "114450",
    "content": "그린케미칼(주)와 100.50억원(최근 매출액대비 24.91%) 규모 공급계약(AI반도체 소재) 체결(계약기간:2026-05-18~2026-12-31) 공시"
  },
  {
    "code": "183300",
    "content": "전일 장 마감 후 보통주 1주 당 1주 배정 무상증자 결정(기준일:2026-05-27, 상장예정:2026-06-15) 공시"
  },
  {
    "code": "123010",
    "content": "전일 장 마감 후 운영자금 확보를 위해 위드윈투자조합91호 대상으로 200.00억원 규모의 사모 전환사채권 발행 결정(전환가액:1,864원, 전환청구일:2027-06-11 ~ 2029-05-11) 공시. 운영자금 확보를 위해 시너직스1호투자조합 대상으로 100.00억원 규모의 사모 전환사채권 발행 결정(전환가액:1,864원, 전환청구일:2027-06-11 ~ 2029-05-11) 공시. 또한, 운영자금 확보 목적으로 위드윈투자조합91호 대상 12,239,902주(199.99억원) 규모 제3자배정 유상증자 결정(발행가:1,634원, 상장예정:2026-06-30) 공시"
  },
  {
    "code": "452280",
    "content": "전일 장 마감 후 분기보고서를 통해 26년1분기 실적 발표, 별도기준 매출액 223.81억원(전년동기대비 +70.70%), 영업이익 62.05억원(전년동기대비 +268.95%), 순손실 51.25억원(전년동기대비 적자전환)"
  },
  {
    "code": "147760",
    "content": "전일 장 마감 후 유상증자로 인한 권리락 효과가 금일 발생한다고 공시. 기준가격은 5,560원임"
  },
  {
    "code": "261200",
    "content": "분기보고서를 통해 26년1분기 실적 발표, 연결기준 매출액 301.93억원(전년동기대비 -7.04%), 영업이익 30.56억원(전년동기대비 +198.55%), 순이익 59.29억원(전년동기대비 흑자전환)"
  },
  {
    "code": "356860",
    "content": "NH투자증권은 동사에 대해 1Q26 실적은 매출액 758억원(+43.1% y-y), 영업이익 107억원(+472.1% y-y, OPM 14.1%)을 기록하며 우호적인 환율 흐름에 힘입어 영업이익 기준 컨센서스 95억원을 소폭 상회하는 호실적 기록했다고 밝힘. 특히, DDR5 내 BVH 공법이 적용된 고부가 제품 비중은 4Q25 73%에서 1Q26 83%까지 확대되며, High-end 제품 수요가 여전히 견조한 흐름을 이어가고 있 음이 확인된다고 밝힘"
  },
  {
    "code": "223250",
    "content": "동사는 언론을 통해 동사가 최대주주로 있는 미국 오가노이드 기술 선도기업 큐리바이오가 올해 1분기 빅파마(글로벌 대형 제약사) 매출에서 의미 있는 도약을 기록했다고 밝힘. 동사가 공개한 큐리바이오 2026년 1분기 카테고리별 매출분석에 따르면, 전체 매출에서 빅파마가 차지하는 비중이 지난해 1분기 5.6%에서 올해 1분기 36.2%로 약 6배 이상 확대되며, 단일 카테고리중 가장 큰 비중을 차지한 것을 전해짐. 빅파마 고객사 수 또한 13곳으로 늘어났으며, 일라이 릴리(Eli Lilly), 노보 노디스크(Novo Nordisk) 등 GLP-1 비만 ·당뇨 치료제로 글로벌 시장을 주도하는 빅파마를 비롯해, 베링거잉겔하임, 버텍스 등 주요 다국적 제약사들이 큐리바이오의 인간 유래 오가노이드 기반 비임상 평가 플랫폼을 활용하고 있는 것으로 알려짐"
  },
  {
    "code": "011320",
    "content": "전일 장 마감 후 보통주 229,886주(10.00억원) 규모 자사주 취득 결정(기간:2026-05-13~2026-08-12) 공시"
  },
  {
    "code": "170030",
    "content": "전일 분기보고서를 통해 1분기 실적 발표, 연결기준 매출액 911.73억원(전년동기대비 +8.34%), 영업이익 55.14억원(전년동기대비 +594.73%), 순이익 50.42억원(전년동기대비 +257.67%)"
  },
  {
    "code": "228850",
    "content": "유진투자증권은 동사에 대해 1분기 수익성 개선으로 어닝서프라이즈를 시현했다고 분석. 특히, 2026년 1분기 잠정실적(연결 기준)은 매출액 368억원, 영업이익 36억원으로 전년동기 대비 매출액은 34.9% 증가하면서 전분기에 이어 연속 큰 폭의 매출 증가세를 유지하였고, 영업이익은 큰 폭으로 수익성이 개선되면서 흑자전환에 성공했으며, 시장 컨센서스(매출액 299억원, 영업이익 18억원) 대비 어닝서프라이즈를 시현했다고 설명. 1분기 실적에서 긍정적인 것은 전분기에 이어 전년동기 대비 매출액이 큰 폭으로 증가했다는 것과 수익성이 크게 개선된 것이라고 밝 힘"
  },
  {
    "code": "219130",
    "content": "전일 장 마감 후 시설자금 등 확보를 위해 대신증권 주식회사 등 대상으로 300.00억원 규모의 사모 전환사채권 발행 결정(전환가액:58,879원, 전환청구일:2027-05-20 ~ 2031-04-20) 공시"
  },
  {
    "code": "413630",
    "content": "동사는 언론을 통해 국내 메이저 조선사와 셔틀탱커 10척에 적용될선박용 특수체인 공급 계약을 체결했다고 밝힘. 이번 수주 물량은 애초 협의되던 9척에서 1척이 추가되며 총 10척 규모로 확대됐다고 언급.최근 미국·이란 간 긴장 고조와 주요국 비축유 확대 정책 등으로 셔틀탱커 시장이 급성장하고 있으며, 이에 따른 국내 대형 조선사들의 후속 발주 가능성도 커지고 있다고 설명"
  },
  {
    "code": "196170",
    "content": "언론에 따르면, 미국특허심판원(PTAB)이 동사의 경쟁사인 할로자임테라퓨틱스(할로자임)의‘엠다제(MDASE)’ 관련 특허를 무효화했다고 전해짐. 미국 특허심판원은 12일(현지시간) 할로자임의 미국 특허(US 11,952,600 B2)에 대한 PGR(Post-Grant Review)에서 ‘최종 서면 결정(Final Written Decision)’을 내리고, 청구항 1~4 및 8~21 을 모두 특허불능(unpatentable)으로 판단했다고 알려짐"
  },
  {
    "code": "491000",
    "content": "전일 장 마감 후 312.44억원 규모 유형자산(토지 및 건물) 양수 결정(양수기준일:2026-07-11) 공시. 양수목적은 차세대 수술로봇 등 글로벌 양산 거 점 'Advanced Manufacturing Facility' 구축임"
  },
  {
    "code": "452260",
    "content": "서울시는 전일 제7차 건축위원회에서 압구정 갤러리아 서관 건립사업, 압구정 갤러리아 동관 건립 사업, 도산대로A 역세권활성화사업 3건을 심의 통과시켰다고 밝힘. 압구정 갤러리아 서관은 강남구 압구정로343 일원, 동관은 압구정로407 일원에서 추진된다며, 두 사업은 압구정로데오역 일대 상업시설을 시민 개방공간과 결합한 건축물로 조성하는 내용임"
  },
  {
    "code": "025560",
    "content": "분기보고서를 통해 26년1분기 실적 발표, 연결기준 매출액 207.38억원(전년동기대비 +336.71%), 영업이익 48.86억원(전년 동기대비 +1,572.08%), 순이익 59.13억원(전년동기대비 +6,163.19%)"
  },
  {
    "code": "403550",
    "content": "전일 장 마감 후 종속회사의 운영자금 마련을 위한 유상증자 참여 목적으로 주식회사 에이펙스 모빌리티 주식 65,000주를 650.00억원에 추가로 취득하기로 결정(취득후지분율:100%, 취득예정일:2026-05-19) 공시"
  },
  {
    "code": "031430",
    "content": "전일 26년1분기 연결기준 매출액 2,956.45억원(전년동기대비 +15.67%), 영업이익 148.29억원(전년동기대비 +452.70%), 순이익 141.97억원(전년동기대비 +214.85%)"
  },
  {
    "code": "004170",
    "content": "키움증권은 동사에 대해 1분기 연결기준 영업이익은 1,978억원(+50% YoY), 지배주주순이익은 1,202억원(+109% YoY)으로 시장 컨센서스를 각각 +18%, +53% 상회했다고 밝힘. 내수 소비경기 호조와 외국인 매출 고성장(+90% YoY)으로 백화점과 신세계인터내셔날의 이익이 가파르게 증가한 가운데, 면세점의 수익성도 시내점 할인율 축소로 예상 보다 크게 개선되었다고 분석. 특히, 백화점 부문의 영업이익은 YoY +331억원 증가하였으나, 감가상각비 증가 영향을 제외한다면, 기존점 매출 성장에 따른 영업이익 증가효과는 460억원 수준(+43% YoY)으로 추산된다고 설명"
  },
  {
    "code": "011070",
    "content": "SK증권은 보고서를 통해 SiP 기판 호황이 돌아왔으며, 5년전 기판 쇼티지 싸이클의 mSAP 기판 산업 수익성은 30%를 상회했다고 밝힘. 동사는 글로벌 Top 10패키징기판사 중 SiP 증설이 가능한 유일한 기업으로, 점유율 상승과 가격 협상력을 동시에 확보하고 있다고 밝힘"
  },
  {
    "code": "097520",
    "content": "대신증권은 동사에 대해 2026년 로봇 및 휴머노이드향 카메라모듈, 액츄에이터 관련 기술 확보 에 주력할 것으로 전망. 특히, 동사는 현대자동차의 1차 공급업체(카메라모듈 및 전장부품)인 동시에 액추에이터 기술을 바탕으로 카메라모듈 부문에서 경쟁력을 보유하고 있다며, 구동계(액추에이터 : A/F, OIS)를 자체적으로 설계, 생산해 모듈 매출을 기록하고 있다고 설명. 또한, 올해 ToF 기반 의 카메라와 ADAS 관련한 전자부품의 기술과 접목하여 로봇/휴머노이드 분야에서 신성장의 기회를 모색할 것으로 예상"
  },
  {
    "code": "000660",
    "content": "현대차증권은 동사에 대해 수요처들의 공격적인 AI Infra 투자의 수혜가 지속될 것으로 전망. 특히, AI 혁신은 더 이상 거부할 수 없는 변화이며 Cloud AI→Edge AI→Physical AI의 변화 속에 AI 반도체 수요도 AIDC→AIRAN→Physical AI 수요로 변화할 경우 우려했던 Chasm의 강도와 기간이 약할 수 있고, 이럴 경우 업황의 변동성이 과거 대비 줄 수 있기 때문에 기존의 P/B Valuation이 동사의 실적 개선 속도와 규모를 충분히 반영할 수 없다고 분석. 다만, P/E Valuation만 적용하기에는 기존 질서를 바꾸는 AI 혁신이 생산 기술 제약과 제도적인 규제 등으로 인해 언제든 작은 Chasm은 발생할 수 있다고 설명"
  },
  {
    "code": "055490",
    "content": "분기보고서를 통해 1분기 실적 발표, 연결기준 매출액 386.32억원(전년동기대비 +24.29%), 영업이익 18.41억원(전년동기대비 흑자전환), 순이익 19.82억원(전년동기대비 흑자전환)"
  },
  {
    "code": "145720",
    "content": "전일 장 마감 후 26년1분기 실적 발표. 연결 기준 매출액 713.83억원(전년동기대비 -7.09%), 영업이익 158.50억원(전년동기대비 +65.39%), 순이익 170.55억원(전년동기대비 +34.49%)"
  },
  {
    "code": "100090",
    "content": "하나증권은 동사에 대해 1Q26 영업이익이 169억원(YoY +52.7%)으로 컨센서스를 상회했다고 밝힘.분기 이익률은 9.7%로 전년대비 5.4%p 개선되었다며, 전사 매출에서 해상풍력의 비중이 70%를 상회한 영향이라고 분석. 또한, 매출 Mix 개선 으로 2분기 이후에도 높은 마진 추세가 지속될 것으로 전망"
  },
  {
    "code": "267250",
    "content": "26년1분기 실적 발표, 연결기준 매출액 19.60조원(전년동기대비 +14.71%), 영업이익 2.83조원(전년동기대비 +120.36%), 순이익 2.02조원(전년동기대비 +160.22%)"
  },
  {
    "code": "192080",
    "content": "26년1분기 연결기준 매출액 2,049.87억 원(전년동기대비 +26.55%), 영업이익 684.71억원(전년동기대비 +25.05%), 순이익 735.49억원(전년동기대비 +60.59%). 26년1분기 별도기준 매 출액 458.14억원(전년동기대비 +4.33%), 영업이익 162.06억원(전년동기대비 +37.07%), 순이익 231.35억원(전년동기대비 +109.55%)"
  },
  {
    "code": "377740",
    "content": "26년1분기 실적 발표, 연결기준 매출액 325.67억원(전년동기대비 +14.48%), 영업이익 63.45억원(전년동기대비 +35.17%), 순이익 412.99억원(전년동기대비 +925.29%)"
  }
]