[
  {
    "code": "062970",
    "content": "동사는 언론을 통해 한국전자통신연구원(ETRI)과 '200Gbs 초고속 신호 전송을 위한 임피던스 정합 실리콘 인터포저 기술'의 기술이전 계약을 체결했다고 밝힘. 해당 기술은 ETRI가 인트라-DC 통신 을 위한 1.6Tbps급 광트랜시버용 광소자 부품 기술 개발 과정에서 확보한 연구 성과로 200Gbps급 고속 신호 기반 구조를 바탕으로 향후 800Gbps, 1.6Tbps 광모듈까지 확장 적용할 수 있다고 설명. 특히, 고속 신호 환경에서도 안정적인 전송 특성을 확보할 수 있어 차세대 광통신 장비 경쟁력에 직결되는 기술로 평가된다고 밝힘"
  },
  {
    "code": "117670",
    "content": "GCT Semiconductor, Inc.와 239.39억원(최근 매출액대비 29.09%) 규모공급계약(반도체 위탁생산) 체결(계약기간:2026-04-02~2026-12-31) 공시"
  },
  {
    "code": "065660",
    "content": "동사는 보도자료를 통해 지방유래 줄기세포 치료제 '알로스템 시트(ALLOSTEM ®, ALLO-ASC-Sheet)' (일반명:니바도스트로셀)이 금일 일본 후생노동성(MHLW)으로부터 제조판매 승인을 취득했다고 밝힘"
  },
  {
    "code": "010280",
    "content": "SK증권은 동사에 대해 2025년 EPS는 354원으로 현재 주가 대비 PER이 2.8배수준이라며, 올해 수익성 개선 추이가 지속되며 2026년 예상 EPS는 450원에 달할 것으로 예상됨에 따라 저평가 매력은 더욱 크게 부각될 것으로 판단. 특히,우리나라 주요 SI 업체들의 평균 PER이 약 8~10배, AX 사업 영위 기업들의 평균 PER이 12~15배 내외인 것을 감안한다면 동사의 주가 상승 잠 재력은 매우 크다고 설명"
  },
  {
    "code": "355690",
    "content": "일부 언론에 따르면, 동사가 글로벌 자동차 부품 기업 현대모비스의 차세대 플랫폼 부품 공급사로 신규 진입한 것으로 전해짐. 여기에 지난해 인수한 조선·방산 부품 전문 자회사 디에스티의 견조한 실적을 바탕으로 모빌리티, 조선, AI(인공지능)을 아우르는 글로벌 전력 솔루션 기업으로 도약할 방침임"
  },
  {
    "code": "358570",
    "content": "동사는 언론을 통해 면역항암제 GI-101A 1상 데이터가 ASCO 구두 발표로 채택됐다고 밝힘. 이번 구두 발표는 전 세계에서 제출된 수천 건의 초록 중 상위 연구만이 선정되는 세션으로, 글로벌 종양학 커뮤니티에서의연구 경쟁력과 파급력을 공식적으로 입증하는 자리라고 설명"
  },
  {
    "code": "063080",
    "content": "언론에 따르면, 한국투자증권은 코인원의 지분 인수 등을 포함해 디지털 자산 사업 진출을 모색 중이 라고 전해짐. 2014년에 설립된 코인원은 업계 점유율 3위 가상자산거래소로, 동사가 지분 21.95%(사업보고서(2025.12) 기준)를 보유한 2대 주주임"
  },
  {
    "code": "382150",
    "content": "동사는 언론을 통해 AI(인공지능) 기반 신약개발 핵심 기술과 관련해 미국 특허 3종을 연이어 확보하며 질병 예측부터 약물 발굴까지 이어지는 전주기 지식재산권(IP) 체계를 구축했다고 밝 힘. 이번에 등 록된 미국 특허는 리보솜 데이터를 활용한 질병 예측 모델과 화합물-단백질 상호작용 예측 기술 2종 등 AI 신약개발의 전 과정을 아우르는 핵심 알고리즘으로, 특히 리보솜 데이터 기반 질병 예측 기술은 피검자의 리보솜 단백질 발현 패턴을 기계학습 모델로 분석해 질병의 유무와 예후를 예측하는 혁신적인 기술로 평가받는다고 알려짐"
  },
  {
    "code": "099430",
    "content": "동사는 언론을 통해 지난 2일 경기도 고양시 킨텍스에서 열린 '코스메틱 인사이드 코리아'(CI KOREA 2026)에서 히알루론산(HA) 필러 '스킨플러스-하이알'(SkinPlus-HYAL)의 임상 유효성과 장기 안전성 데이터를 발표했다고 밝힘. 동사 이광훈 의료 기기 연구소장은 '디비닐 설폰(DVS) 가교 기술을 적용한 HA 필러 SkinPlus-HYAL의 임상 유효성 및 장기 안전성'을 주제로 발표를 진행했음"
  },
  {
    "code": "306620",
    "content": "스터닝밸류리서치는 동사에 대해 과거 일본 기업들이 독점하던 MLCC(적층세라믹콘덴서) 커팅 장비를 국산화했다며, 핵심 파트너사인 삼성전기 내 약 70% 이상의 점유율을 확보했다고 밝힘. 최근 AI 서버 및 전장용 MLCC 시장이 급격히 팽창함에 따라, 고정밀 절단 기술인 ‘Saw & Sorter’ 솔루션의 중요성이 더욱 부각되고 있다며, 2025년으로부터 이월된 200억원 규모의 수주 잔고는 이러한 기술적 신뢰도를 증명하고, 2026년 상반기 매출의 탄탄한 기초가 될 것으로 전망"
  },
  {
    "code": "177900",
    "content": "동사는 언론을 통해 차세대융합기술연구원에서 주관하는 '2026년 도 경기도 팹리스 수요연계 양산지원 사업'의 양산성능평가 과제에 최종 선정됐다고 밝힘. 이번 사업은 경기도 내 역량 있는 팹리스 기업의기술 상용화를 돕기 위해 수요처와 연계된 양산 성능 검증을 지원하는 사업임. 동사가 양산에 나서는 대상 칩 'TDP500MU'은 전량 외산에 의존하던 듀얼밴드(Dual-Band) 보안 태그 IC를 국산화한 제품임"
  },
  {
    "code": "300080",
    "content": "글로벌 IT기업과 38.77억원(최근 매출액대비 10.78%) 규모 공급계약(AI(인공지능) 기반 언어 모델의 연구 및 개발용 데이터 공급) 체결(계약기간:2025-10-02~2026-11-10) 공시"
  },
  {
    "code": "446540",
    "content": "전일 장 마감 후 시설자금 등 확보 목적으로 Whitston Materials Technology Co., Ltd.(기타) 대상 3,115,362주(114.02억원) 규모 제3자배정 유상증자 결정(발행가:3,660원, 상장예정:2026-05-29) 공시"
  },
  {
    "code": "304360",
    "content": "일부 언론에 따르면, 동사가 개발 중인 파킨슨병 세포치료제 ‘TED-A9’의 국내 임상 1/2a상 탑라인(Top Line) 데이터를 이르면내달 말에서 6월 중순 사이 발표할 예정이라고 전해짐. 이번 탑라인 데이터는 동사가 준비 중인 미국 상업화 임상시험계획서(IND) 제출을 위 한 핵심 근거 자료로 활용될 계획이라고 알려짐"
  },
  {
    "code": "016600",
    "content": "전일 장 마감 후 보통주 3,727,090주 소각 결정(소각예정일:2026-06-05) 공시. 소각예정금액은 17.40억원임. 또한, 기업가치 제고 계획 예고(2026년 4월 16일 이내) 공시"
  },
  {
    "code": "100840",
    "content": "신한투자증권은 동사에 대해 미주 지역 LNG 프로젝트 발주 대기에 따른 수주잔고 방어가 기대된다고 밝힘. 그린필드 델핀(4기, 1,330만톤),커먼웰스(6기, 950만톤) 및 CP2(36기, 2,000만톤), 브라운필드 Plaquemines(32기, 3,000만톤) 등 대규모 프로젝트의 FID를 논의 중이라며, 신규 수주는 기존 사우디 발주처와의 레퍼런스를 바탕으로 중동 지역의 단기 수주 공백을 상쇄할 것으로 전망. 아울러 중동 사태에 따른 실적변동성을 완전히 상쇄하기는 어려우나, 수주잔고 유지 측면에서 긍정적이라며, 27년 드래곤 가스전 유입에 따른 애틀랜틱 LNG(4기, 1,500만톤) 개보수 수요가 기대된다고 밝힘"
  },
  {
    "code": "009150",
    "content": "SK증권은 동사에 대해 1분기 영업이익은 2,672억원(+33%, YoY)으로 전망된다며, 이는 일회성 비용이 반영된 손익으로, 제외 시 이익규모는 기존 추정치(2,842억원)를 크게 상회할 것으로 전망. 이와 관련, 연초부터 MLCC 주문이 늘고 있는 가운데, FCBGA는 올 해 연말 또는 내년 연초 풀캐파 가동을 향해 가파르게 상승 중이라고 설명. 또한, 주요 부품들의 ASP도 오르고 있다며, 특히 FCBGA의 가격은 지금이 상승 흐름의 초입이라고 분석. 5년 전 싸이클에서 일부 기판의 가격은 100% 이상 올랐었으며, 이에 따라 2분기 영업이익은 3,421억원(+61%)을 달성할 것으로 추정(환율가정, 1,450원)"
  },
  {
    "code": "103140",
    "content": "일부 언론에 따르면, 매각 추진설에 대해 '사실무근'이라고 부인했던 동사가 기업 밸류에이션을 평가받는 절차에 들어간 것으로 전해짐. IB(투자은행)업계와 방위산업계에 따르면, 동사는 지난 3월 풍문 또는 보도에 대한 해명에 대한 추가 공시를 낼 예정이라며, \"기업가치 및 주주가치 제고를 위한 사업구조 개편 방안을 검토하고 있는 것은 맞다\"고 밝힘. IB업계 등에서 매각 추진설이 제기됐지만 동사는 초기에 사실 무근이란 입장을 냈다가 해명 공시를 통해 포괄적인 사업 구조 개편 검토 자체는 인정했다고 알 려짐"
  },
  {
    "code": "027970",
    "content": "동사는 언론을 통해 종이 기반 친환경 포장재에 대한 상담 문의가 직전 대비 30~40% 늘었다고 밝힘. 이는 최근 패키징 시장 내 재활용 확대 요구가 커진 데다, 중동 리스크에 따른 비닐·플라스틱 원료 수급 불안이 겹친 결과임. 동사의 주요 제품으로는 친환경 포장재 '그린실드(Green-Shield)',친환경 종이 연포장재 '지플렉스(G-Flex)', 친환경 이형지 등이 있음"
  },
  {
    "code": "030000",
    "content": "DS투자증권은 동사에 대해 글로벌 사업 효율화와 디지털/AI 투자를 병행해 실적 성장과 수익성 개선의 발판을 마련하고있다고 밝힘. 23년부터 지속적으로 글로벌 부진 자회사들을 정리하고 중복 기능을 통합하는 등 사업 효율화에 나서고 있으며, 이번 유럽 사업 구조 재편에 따른 인건비 감소가 기대된다고 설명. 또한, AI 관련 인력과 인프라 투자를 통해 퍼포먼스 마케팅 역량을 강화하고 계열과 비계열 광고주 대행 영역 확대, 추가적인 비용 효율화도 가능해질 것으로 전망. 이에 2분기부터 비용 절감 효과가 나타나기 시작하고 주요 스포츠 이벤트 관련 광고 물량이 확대되며 실적 개선을 시현할 것이라고 밝힘"
  }
]